fastmdanalysis/__init__.py
fastmdanalysis/__main__.py
fastmdanalysis/datasets.py
fastmdanalysis/analysis/__init__.py
fastmdanalysis/analysis/analyze.py
fastmdanalysis/analysis/base.py
fastmdanalysis/analysis/cluster.py
fastmdanalysis/analysis/dimred.py
fastmdanalysis/analysis/hbonds.py
fastmdanalysis/analysis/rg.py
fastmdanalysis/analysis/rmsd.py
fastmdanalysis/analysis/rmsf.py
fastmdanalysis/analysis/sasa.py
fastmdanalysis/analysis/ss.py
fastmdanalysis/cli/__init__.py
fastmdanalysis/cli/_common.py
fastmdanalysis/cli/analyze.py
fastmdanalysis/cli/main.py
fastmdanalysis/cli/simple.py
fastmdanalysis/data/__init__.py
fastmdanalysis/data/trp_cage.dcd
fastmdanalysis/data/trp_cage.pdb
fastmdanalysis/utils/__init__.py
fastmdanalysis/utils/io.py
fastmdanalysis/utils/logging.py
fastmdanalysis/utils/slideshow.py
fastmdanalysis-1.0.0.dist-info/METADATA
fastmdanalysis-1.0.0.dist-info/WHEEL
fastmdanalysis-1.0.0.dist-info/entry_points.txt
fastmdanalysis-1.0.0.dist-info/licenses/LICENSE
fastmdanalysis-1.0.0.dist-info/RECORD
