Metadata-Version: 2.4
Name: fastmdanalysis
Version: 1.0.0
Summary: Software for automated MD trajectory analysis
Project-URL: Repository, https://github.com/aai-research-lab/FastMDAnalysis
Project-URL: Documentation, https://fastmdanalysis.readthedocs.io
Project-URL: Issues, https://github.com/aai-research-lab/FastMDAnalysis/issues
Author-email: Adekunle Aina <kunleaina@gmail.com>
License: MIT License
License-File: LICENSE
Keywords: molecular dynamics,trajectory analysis
Classifier: License :: OSI Approved :: MIT License
Classifier: Operating System :: OS Independent
Classifier: Programming Language :: Python :: 3
Requires-Python: >=3.9
Requires-Dist: cairosvg>=2.7
Requires-Dist: matplotlib>=3.5.0
Requires-Dist: mdtraj>=1.9.7
Requires-Dist: numpy>=1.21.0
Requires-Dist: pillow>=10.0
Requires-Dist: python-pptx>=0.6.21
Requires-Dist: pyyaml>=6.0
Requires-Dist: scikit-learn>=1.0.0
Requires-Dist: scipy>=1.10
Provides-Extra: dev
Requires-Dist: pytest-cov>=4.0; extra == 'dev'
Requires-Dist: pytest>=7.0; extra == 'dev'
Provides-Extra: test
Requires-Dist: pytest-cov>=4.0; extra == 'test'
Requires-Dist: pytest>=7.0; extra == 'test'
